kombin_algo_pranavpatel_ca/Table.py
kombin_algo_pranavpatel_ca/__init__.py
kombin_algo_pranavpatel_ca-1.0.3.dist-info/METADATA
kombin_algo_pranavpatel_ca-1.0.3.dist-info/WHEEL
kombin_algo_pranavpatel_ca-1.0.3.dist-info/licenses/LICENSE
kombin_algo_pranavpatel_ca-1.0.3.dist-info/RECORD
