Metadata-Version: 2.4
Name: kombin_algo_pranavpatel_ca
Version: 1.0.3
Summary: KombiN is a library for bijectively mapping all ordered pairs from two finite sets into a single linear index. It orders pairs by ascending weight (sum of indices) using a three-region zig-zag algorithm, enabling O(1) bidirectional lookups between pairs and indices.
Project-URL: Homepage, https://github.com/octopranav/KombiN
Project-URL: Bug Tracker, https://github.com/octopranav/KombiN/issues
Author-email: Pranavkumar Patel <contact@pranavpatel.ca>
License-File: LICENSE
Classifier: License :: OSI Approved :: MIT License
Classifier: Operating System :: OS Independent
Classifier: Programming Language :: Python :: 3
Requires-Python: >=3.6
